polydup-0.9.3.data/scripts/.gitkeep
polydup-0.9.3.dist-info/METADATA
polydup-0.9.3.dist-info/WHEEL
polydup-0.9.3.dist-info/entry_points.txt
polydup/__init__.py
polydup/__main__.py
polydup/_cli.py
polydup/polydup.cpython-39-darwin.so
polydup-0.9.3.dist-info/RECORD
