Metadata-Version: 2.4
Name: polydup
Version: 0.9.3
Classifier: Development Status :: 3 - Alpha
Classifier: Intended Audience :: Developers
Classifier: License :: OSI Approved :: MIT License
Classifier: License :: OSI Approved :: Apache Software License
Classifier: Programming Language :: Rust
Classifier: Programming Language :: Python :: 3
Classifier: Programming Language :: Python :: 3.8
Classifier: Programming Language :: Python :: 3.9
Classifier: Programming Language :: Python :: 3.10
Classifier: Programming Language :: Python :: 3.11
Classifier: Programming Language :: Python :: 3.12
Classifier: Environment :: Console
Summary: Cross-language duplicate code detector - Python library and CLI
Keywords: duplicate,code,detection,rust,tree-sitter,cli
License: MIT OR Apache-2.0
Requires-Python: >=3.8
